ict_szpu/DigitalHuman.py
ict_szpu/Math.py
ict_szpu/Public.py
ict_szpu/Robot.py
ict_szpu/UAV.py
ict_szpu/__init__.py
ict_szpu/core.py
ict_vscl/DigitalHuman.py
ict_vscl/Public.py
ict_vscl/Robot.py
ict_vscl/UAV.py
ict_vscl/__init__.py
ict_vscl/core.py
ict_szpu-1.0.10.dist-info/METADATA
ict_szpu-1.0.10.dist-info/WHEEL
ict_szpu-1.0.10.dist-info/top_level.txt
ict_szpu-1.0.10.dist-info/RECORD
