Metadata-Version: 2.1
Name: ict-szpu
Version: 1.0.10
Summary: 深职院智能ict三维编程拓展组件
Requires-Dist: websocket-client
